light_distribution/__init__.py
light_distribution/analyzer.py
light_distribution_analysis/__init__.py
light_distribution_analysis/analyzer.py
light_distribution_analysis-0.2.0.1.dist-info/LICENSE.md
light_distribution_analysis-0.2.0.1.dist-info/METADATA
light_distribution_analysis-0.2.0.1.dist-info/WHEEL
light_distribution_analysis-0.2.0.1.dist-info/top_level.txt
light_distribution_analysis-0.2.0.1.dist-info/RECORD
