Metadata-Version: 2.1
Name: light-distribution-analysis
Version: 0.2.0.1
Summary: Analyze the flux of images based on wavelength and frequency
Author: Viktor Veselov
Author-email: lipovkaviktor@yahoo.com
Project-URL: Bug Tracker, https://github.com/SweatyCrayfish/light-distribution-analysis/issues
Project-URL: Source Code, https://github.com/SweatyCrayfish/light-distribution-analysis
Keywords: light distribution analysis flux wavelength frequency images
Classifier: Development Status :: 3 - Alpha
Classifier: Intended Audience :: Science/Research
Classifier: License :: OSI Approved :: MIT License
Classifier: Programming Language :: Python :: 3.7
Classifier: Programming Language :: Python :: 3.8
Classifier: Programming Language :: Python :: 3.9
Classifier: Programming Language :: Python :: 3.10
Classifier: Programming Language :: Python :: 3.11
License-File: LICENSE.md
Requires-Dist: opencv-python
Requires-Dist: numpy
Requires-Dist: matplotlib
